[
  {
    "number": 1,
    "name": "Johannesburg",
    "category": "Branches"
  },
  {
    "number": 2,
    "name": "Bloemfontein",
    "category": "Branches"
  },
  {
    "number": 3,
    "name": "Boksburg",
    "category": "Branches"
  },
  {
    "number": 4,
    "name": "Glen",
    "category": "Branches"
  },
  {
    "number": 5,
    "name": "Tembisa",
    "category": "Branches"
  },
  {
    "number": 6,
    "name": "Randburg",
    "category": "Branches"
  },
  {
    "number": 7,
    "name": "Sandton",
    "category": "Branches"
  },
  {
    "number": 8,
    "name": "Alex",
    "category": "Branches"
  }
]